tipboard/__init__.py
tipboard/api.py
tipboard/app.py
tipboard/console.py
tipboard/parser.py
tipboard/redis_utils.py
tipboard/settings.py
tipboard/defaults/layout_config.yaml
tipboard/defaults/settings-local.py
tipboard/extras/README.rst
tipboard/extras/client_code_example.py
tipboard/extras/fabfile.py
tipboard/extras/jira-ds.js
tipboard/extras/jira-ds.py
tipboard/static/css/jquery.jqplot.css
tipboard/static/css/layout.css
tipboard/static/css/reset.css
tipboard/static/fonts/MISO_LICENSE
tipboard/static/fonts/miso-light-webfont.eot
tipboard/static/fonts/miso-light-webfont.svg
tipboard/static/fonts/miso-light-webfont.ttf
tipboard/static/fonts/miso-light-webfont.woff
tipboard/static/fonts/miso-webfont.eot
tipboard/static/fonts/miso-webfont.svg
tipboard/static/fonts/miso-webfont.ttf
tipboard/static/fonts/miso-webfont.woff
tipboard/static/js/flipboard.js
tipboard/static/js/tipboard.js
tipboard/static/js/lib/html5shiv.js
tipboard/static/js/lib/jquery.fullscreen.js
tipboard/static/js/lib/jquery.js
tipboard/static/js/lib/require.js
tipboard/static/js/lib/simplify.js
tipboard/static/js/lib/jqplot/excanvas.min.js
tipboard/static/js/lib/jqplot/jquery.jqplot.js
tipboard/static/js/lib/jqplot/plugins/jqplot.BezierCurveRenderer.js
tipboard/static/js/lib/jqplot/plugins/jqplot.barRenderer.js
tipboard/static/js/lib/jqplot/plugins/jqplot.blockRenderer.js
tipboard/static/js/lib/jqplot/plugins/jqplot.bubbleRenderer.js
tipboard/static/js/lib/jqplot/plugins/jqplot.canvasAxisLabelRenderer.js
tipboard/static/js/lib/jqplot/plugins/jqplot.canvasAxisTickRenderer.js
tipboard/static/js/lib/jqplot/plugins/jqplot.canvasOverlay.js
tipboard/static/js/lib/jqplot/plugins/jqplot.canvasTextRenderer.js
tipboard/static/js/lib/jqplot/plugins/jqplot.categoryAxisRenderer.js
tipboard/static/js/lib/jqplot/plugins/jqplot.ciParser.js
tipboard/static/js/lib/jqplot/plugins/jqplot.cursor.js
tipboard/static/js/lib/jqplot/plugins/jqplot.dateAxisRenderer.js
tipboard-1.4.3.dist-info/METADATA
tipboard-1.4.3.dist-info/RECORD
tipboard-1.4.3.dist-info/WHEEL
tipboard-1.4.3.dist-info/entry_points.txt
tipboard-1.4.3.dist-info/top_level.txt
