Metadata-Version: 2.1
Name: tipboard
Version: 1.4.3
Summary: Tipboard - a flexible solution for creating your dashboards.
Home-page: http://tipboard.allegrogroup.com
Author: Allegro Group and Contributors
Author-email: pylabs@allegro.pl
License: Apache Software License v2.0
Platform: any
Requires-Dist: mock (==1.0.1)
Requires-Dist: PyYAML (==3.10)
Requires-Dist: redis (==2.7.5)
Requires-Dist: requests (==1.2.3)
Requires-Dist: six (>=1.4.1)
Requires-Dist: tornado-redis (==2.4.2)
Requires-Dist: tornado (==3.0.1)
Requires-Dist: docopt (==0.6.1)
Requires-Dist: raven (==3.5.2)
Requires-Dist: Sphinx (==1.2.2)
Requires-Dist: sphinxcontrib-httpdomain (==1.3.0)
